sansjson/README.md
sansjson/__init__.py
sansjson/utils.py
sansjson/tests/conftest.py
sansjson/tests/test_sort_dict.py
sansjson/tests/test_sort_list.py
sansjson/tests/test_sorter.py
sansjson-0.2.0.dist-info/METADATA
sansjson-0.2.0.dist-info/WHEEL
sansjson-0.2.0.dist-info/licenses/LICENSE
sansjson-0.2.0.dist-info/RECORD
