Metadata-Version: 2.1
Name: sansjson
Version: 0.2.0
Summary: Your friendly neighborhood JSON sorter helper
Project-URL: Homepage, https://github.com/nickumia/sansjson
Project-URL: Bug Tracker, https://github.com/nickumia/sansjson/issues
Author-email: nickumia <nickumia6@gmail.com>
License-File: LICENSE
Classifier: License :: OSI Approved :: MIT License
Classifier: Operating System :: OS Independent
Classifier: Programming Language :: Python :: 3
Requires-Python: >=3.7
